filecheckize/__init__.py
filecheckize/_version.py
filecheckize/main.py
filecheckize-0.2.dist-info/LICENSE
filecheckize-0.2.dist-info/METADATA
filecheckize-0.2.dist-info/WHEEL
filecheckize-0.2.dist-info/entry_points.txt
filecheckize-0.2.dist-info/top_level.txt
filecheckize-0.2.dist-info/RECORD
